udi_interface/__init__.py
udi_interface/custom.py
udi_interface/interface.py
udi_interface/isy.py
udi_interface/node.py
udi_interface/oauth.py
udi_interface/polylogger.py
udi_interface/startupdiag.py
udi_interface/udi_interface.py
udi_interface-3.3.18.dist-info/licenses/LICENSE
udi_interface-3.3.18.dist-info/METADATA
udi_interface-3.3.18.dist-info/WHEEL
udi_interface-3.3.18.dist-info/top_level.txt
udi_interface-3.3.18.dist-info/RECORD
