Metadata-Version: 2.4
Name: udi_interface
Version: 3.3.18
Summary: UDI Python Interface for Polyglot version 3
Home-page: https://github.com/UniversalDevicesInc/udi_python_interface
Author: Universal Devices Inc.
Author-email: bpaauwe@yahoo.com
License: MIT
Classifier: Development Status :: 5 - Production/Stable
Classifier: License :: OSI Approved :: MIT License
Classifier: Programming Language :: Python :: 3.6
Classifier: Programming Language :: Python :: 3.7
Classifier: Programming Language :: Python :: 3.8
Classifier: Programming Language :: Python :: 3.9
Classifier: Programming Language :: Python :: 3.11
Requires-Python: >3.9
License-File: LICENSE
Requires-Dist: paho-mqtt>=2.1.0
Requires-Dist: python-dotenv
Requires-Dist: markdown2
Requires-Dist: netifaces
Requires-Dist: requests
Requires-Dist: pyisy!=2.1.5,<3.0.0,>2.0
Dynamic: author
Dynamic: author-email
Dynamic: classifier
Dynamic: home-page
Dynamic: license
Dynamic: license-file
Dynamic: requires-dist
Dynamic: requires-python
Dynamic: summary
